{"artboards":[{"name":"グループ 24831","type":"group","bounds":{"width":861.001953125,"height":537,"x":2730.99853515625,"y":-2205},"style":{},"id":"35ecdde5-00fa-4bb2-9aae-e280c7d2a234","transform":{"a":1,"b":0,"c":0,"d":1,"e":0,"f":0},"children":[{"name":"グループ 24633","type":"group","bounds":{"width":861.001953125,"height":537,"x":2730.99853515625,"y":-2205},"style":{},"id":"f0ef8517-7597-4622-a4e7-aa6a1ffd53b2","transform":{"a":1,"b":0,"c":0,"d":1,"e":660,"f":1141.00048828125},"children":[{"name":"Features_card","type":"symbolinstance","bounds":{"width":420.00146484375,"height":537,"x":3171.9990234375,"y":-2205},"style":{},"id":"b1338041-c941-4a80-8d11-8578ad8f0652","transform":{"a":1,"b":0,"c":0,"d":1,"e":640.9990234375,"f":1384},"children":[{"name":"グループ 24635","type":"group","bounds":{"width":420.00146484375,"height":537.0001220703125,"x":3171.9990234375,"y":-2205},"style":{},"id":"a1cfe8ce-5ba5-4868-bcb4-a5ffebae181e","transform":{"a":1,"b":0,"c":0,"d":1,"e":0.00146484375,"f":0.013072967529296875},"children":[{"name":"グループ 24069","type":"group","bounds":{"width":420.00146484375,"height":537,"x":3171.9990234375,"y":-2205},"style":{},"id":"12e0e61b-baad-4f64-a6eb-ffb79c7396e0","transform":{"a":1,"b":0,"c":0,"d":1,"e":-0.00146484375,"f":-0.013072967529296875},"children":[{"name":"グループ 24098","type":"group","bounds":{"width":420.00146484375,"height":537,"x":3171.9990234375,"y":-2205},"style":{},"id":"2c9652cb-3eb0-40ae-8d3d-198207d7a514","transform":{"a":1,"b":0,"c":0,"d":1,"e":0,"f":-4.941618403538073e-13},"children":[{"name":"長方形 1410","type":"rectangle","bounds":{"width":420.00146484375,"height":537,"x":3171.9990234375,"y":-2205},"style":{"fill":{"type":"color","rgba":"rgba(255, 255, 255, 255)","hex":"#FFFFFF"},"stroke":{"color":{"type":"color","rgba":"rgba(34, 34, 34, 255)","hex":"#222222"},"width":2},"cornerRadii":{"topLeft":10,"topRight":10,"bottomRight":10,"bottomLeft":10}},"id":"e0106a3c-d8a4-4795-b5d5-57aabeb0a096","transform":{"a":1,"b":0,"c":0,"d":1,"e":0,"f":0},"children":[]}]}]},{"name":"グループ 24609","type":"group","bounds":{"width":340.00146484375,"height":445.0001220703125,"x":3211.9990234375,"y":-2165},"style":{},"id":"5058f90f-9f24-4db5-b2c9-56a714cc9197","transform":{"a":1,"b":0,"c":0,"d":1,"e":39.99853515625,"f":-18.66845703125},"children":[{"name":"アセット 8@3x","type":"rectangle","bounds":{"width":340,"height":200,"x":3211.9990234375,"y":-1920},"style":{"fill":{"type":"image"}},"id":"f01adcf7-136e-4f69-99dd-96b77f19a6b5","transform":{"a":1,"b":0,"c":0,"d":1,"e":0,"f":303.6553955078125},"children":[]},{"name":"瓦の重ね幅を70㎜にし、従来の水返し壁と合わせて、雨水の巻き込みを大幅に軽減し、雨漏りしにくい構造を実現しました。","type":"text","bounds":{"width":340,"height":125,"x":3212.00048828125,"y":-2065},"style":{"fontFamily":"Zen Kaku Gothic New","fontSize":20,"fontStyle":"Medium","textAlign":"left","lineHeight":32,"letterSpacing":60,"fill":{"type":"color","rgba":"rgba(34, 34, 34, 255)","hex":"#222222"}},"id":"6dabe8c1-09c2-446b-80b7-f3d34414b03f","transform":{"a":1,"b":0,"c":0,"d":1,"e":0.00146484375,"f":158.65538024902344},"text":"瓦の重ね幅を70㎜にし、従来の水返し壁と合わせて、雨水の巻き込みを大幅に軽減し、雨漏りしにくい構造を実現しました。","children":[]},{"name":"長方形 1569","type":"rectangle","bounds":{"width":340,"height":2,"x":3212.00048828125,"y":-2087},"style":{"fill":{"type":"color","rgba":"rgba(32, 174, 229, 255)","hex":"#20AEE5"}},"id":"faf720c8-0f03-4d50-976c-a70c4e8d74fc","transform":{"a":1,"b":0,"c":0,"d":1,"e":0.00146484375,"f":136.65538024902344},"children":[]},{"name":"グループ 24607","type":"group","bounds":{"width":213,"height":58,"x":3212.00048828125,"y":-2165},"style":{},"id":"05a8eaa5-f204-4868-9eab-dbc4127792c8","transform":{"a":1,"b":0,"c":0,"d":1,"e":-59.99853515625,"f":-14.013072967529297},"children":[{"name":"防水性能","type":"text","bounds":{"width":167,"height":58,"x":3258.00048828125,"y":-2165},"style":{"fontFamily":"Zen Kaku Gothic New","fontSize":40,"fontStyle":"Black","textAlign":"left","lineHeight":56,"letterSpacing":60,"fill":{"type":"color","rgba":"rgba(32, 174, 229, 255)","hex":"#20AEE5"}},"id":"e1362280-f68e-4395-a85b-1fd9cca1f406","transform":{"a":1,"b":0,"c":0,"d":1,"e":106,"f":118.66845703125},"text":"防水性能","children":[]},{"name":"02","type":"text","bounds":{"width":26,"height":24,"x":3212.00048828125,"y":-2148},"style":{"fontFamily":"Montserrat","fontSize":20,"fontStyle":"Bold Italic","textAlign":"left","lineHeight":32,"letterSpacing":60,"fill":{"type":"color","rgba":"rgba(32, 174, 229, 255)","hex":"#20AEE5"}},"id":"60638067-fe28-404f-af18-2a08d01f67fd","transform":{"a":1,"b":0,"c":0,"d":1,"e":60,"f":108.66845703125},"text":"02","children":[]}]}]}]},{"name":"_Cost","type":"text","bounds":{"width":37,"height":15,"x":3535.00048828125,"y":-1704},"style":{"opacity":0.699999988079071,"fontFamily":"Montserrat","fontSize":12,"fontStyle":"Bold Italic","textAlign":"right","lineHeight":32,"letterSpacing":60,"fill":{"type":"color","rgba":"rgba(32, 174, 229, 255)","hex":"#20AEE5"}},"id":"b841753a-7728-415e-91cf-22367dde7d5e","transform":{"a":1,"b":0,"c":0,"d":1,"e":400.00146484375,"f":513.0001220703125},"text":"_Cost","children":[]}]},{"name":"Features_card","type":"symbolinstance","bounds":{"width":421.00048828125,"height":536.9998779296875,"x":2730.99853515625,"y":-2205},"style":{},"id":"f7e79795-1ac9-4b90-98ab-2f636f555997","transform":{"a":1,"b":0,"c":0,"d":1,"e":199.99853515625,"f":1384.0001220703125},"children":[{"name":"グループ 24635","type":"group","bounds":{"width":421.00048828125,"height":537,"x":2730.99853515625,"y":-2205},"style":{},"id":"eda92a1a-5583-4df9-8743-364cf3058fe7","transform":{"a":1,"b":0,"c":0,"d":1,"e":0,"f":0.013072967529296875},"children":[{"name":"グループ 24069","type":"group","bounds":{"width":421.00048828125,"height":537,"x":2730.99853515625,"y":-2204.999755859375},"style":{},"id":"dcfdd2ef-a6ac-4d5c-a8c4-4556a56f484f","transform":{"a":1,"b":0,"c":0,"d":1,"e":0,"f":0.002685546875},"children":[{"name":"グループ 24098","type":"group","bounds":{"width":421.00048828125,"height":537,"x":2730.99853515625,"y":-2205},"style":{},"id":"77bd3a79-ad25-458c-a843-284fdd8c3ba1","transform":{"a":1,"b":0,"c":0,"d":1,"e":0,"f":-0.002685546875},"children":[{"name":"長方形 1410","type":"rectangle","bounds":{"width":421.00048828125,"height":537,"x":2730.99853515625,"y":-2205},"style":{"fill":{"type":"color","rgba":"rgba(32, 174, 229, 255)","hex":"#20AEE5"},"stroke":{"color":{"type":"color","rgba":"rgba(34, 34, 34, 255)","hex":"#222222"},"width":2},"cornerRadii":{"topLeft":10,"topRight":10,"bottomRight":10,"bottomLeft":10}},"id":"5c778186-5af4-47bc-b7c8-97ea0d875f37","transform":{"a":1,"b":0,"c":0,"d":1,"e":0,"f":-0.01318359375},"children":[]}]}]},{"name":"グループ 24609","type":"group","bounds":{"width":341.00048828125,"height":443,"x":2770.99853515625,"y":-2165},"style":{},"id":"978a2341-1b61-43f0-8b1e-8b2ab91f95da","transform":{"a":1,"b":0,"c":0,"d":1,"e":39.99853515625,"f":-18.66845703125},"children":[{"name":"アセット 9@3x","type":"rectangle","bounds":{"width":340,"height":230,"x":2771.9990234375,"y":-1952},"style":{"fill":{"type":"image"}},"id":"269fda08-577c-40a6-b8d5-adc085bc919d","transform":{"a":1,"b":0,"c":0,"d":1,"e":1.001953125,"f":271.6552734375},"children":[]},{"name":"くちかぎ部分に2㎝の重なり部分を設けました。瓦同士が押さえ合って浮き上げりを防ぎます。","type":"text","bounds":{"width":340,"height":93,"x":2770.9990234375,"y":-2065},"style":{"fontFamily":"Zen Kaku Gothic New","fontSize":20,"fontStyle":"Medium","textAlign":"left","lineHeight":32,"letterSpacing":60,"fill":{"type":"color","rgba":"rgba(255, 255, 255, 255)","hex":"#FFFFFF"}},"id":"f42e224e-6d27-45c1-a1f0-7d0409e8ac8d","transform":{"a":1,"b":0,"c":0,"d":1,"e":0.001953125,"f":158.65538024902344},"text":"くちかぎ部分に2㎝の重なり部分を設けました。瓦同士が押さえ合って浮き上げりを防ぎます。","children":[]},{"name":"長方形 1569","type":"rectangle","bounds":{"width":340,"height":2,"x":2770.99853515625,"y":-2087},"style":{"fill":{"type":"color","rgba":"rgba(255, 255, 255, 255)","hex":"#FFFFFF"},"stroke":{"color":{"type":"color","rgba":"rgba(255, 255, 255, 255)","hex":"#FFFFFF"},"width":1}},"id":"6e8a051e-5dac-4e77-a520-8732e0b03fb0","transform":{"a":1,"b":0,"c":0,"d":1,"e":0.00146484375,"f":136.65538024902344},"children":[]},{"name":"グループ 24607","type":"group","bounds":{"width":209,"height":58,"x":2771.99853515625,"y":-2165},"style":{},"id":"45fdaad6-c2f2-48c7-9c48-64fc52aa86e5","transform":{"a":1,"b":0,"c":0,"d":1,"e":-59.99853515625,"f":-14.013072967529297},"children":[{"name":"防災機能","type":"text","bounds":{"width":167,"height":58,"x":2813.99853515625,"y":-2165},"style":{"fontFamily":"Zen Kaku Gothic New","fontSize":40,"fontStyle":"Black","textAlign":"left","lineHeight":56,"letterSpacing":60,"fill":{"type":"color","rgba":"rgba(255, 255, 255, 255)","hex":"#FFFFFF"}},"id":"a7300a07-42d2-487c-8a10-5d80f8fb5cb2","transform":{"a":1,"b":0,"c":0,"d":1,"e":103,"f":118.66845703125},"text":"防災機能","children":[]},{"name":"01","type":"text","bounds":{"width":23,"height":24,"x":2771.99853515625,"y":-2148},"style":{"fontFamily":"Montserrat","fontSize":20,"fontStyle":"Bold Italic","textAlign":"left","lineHeight":32,"letterSpacing":60,"fill":{"type":"color","rgba":"rgba(255, 255, 255, 255)","hex":"#FFFFFF"}},"id":"67157e36-457f-45db-8c63-816d833adf4a","transform":{"a":1,"b":0,"c":0,"d":1,"e":61,"f":108.66845703125},"text":"01","children":[]}]}]}]},{"name":"_Noise","type":"text","bounds":{"width":46,"height":15,"x":3084.99853515625,"y":-1704},"style":{"fontFamily":"Montserrat","fontSize":12,"fontStyle":"Bold Italic","textAlign":"right","lineHeight":32,"letterSpacing":60,"fill":{"type":"color","rgba":"rgba(255, 255, 255, 255)","hex":"#FFFFFF"}},"id":"d7d6fb6d-09e7-4ec6-9b6d-4cf9af4471b6","transform":{"a":1,"b":0,"c":0,"d":1,"e":400,"f":512.9998779296875},"text":"_Noise","children":[]}]}]}]}]}